{
  "timestamp": "2026-04-24T23:19:53.777183Z",
  "channels": {
    "ch101": 210.0,
    "ch102": 90.0,
    "ch103": 20.0,
    "ch104": 30.0,
    "ch105": 10.0,
    "ch106": 150.0,
    "ch107": 760.0,
    "ch108": 320.0,
    "ch109": 71770.0,
    "ch110": 90.0,
    "ch111": 32640.0,
    "ch112": 31910.0,
    "ch113": 170.0,
    "ch114": 130.0,
    "ch115": 200.0,
    "ch116": 220.0,
    "ch117": 22260.0,
    "ch118": 20.0,
    "ch201": 17480.0,
    "ch202": 1160.0,
    "ch203": 4660.0,
    "ch204": 15140.0,
    "ch205": 374510.0,
    "ch206": 2570.0,
    "ch207": 25310.0,
    "ch208": 5200.0,
    "ch209": 430.0
  },
  "coincidences": {}
}