{
  "timestamp": "2026-04-25T13:46:01.043299Z",
  "channels": {
    "ch101": 220.0,
    "ch102": 80.0,
    "ch103": 30.0,
    "ch104": 30.0,
    "ch105": 20.0,
    "ch106": 110.0,
    "ch107": 660.0,
    "ch108": 270.0,
    "ch109": 69480.0,
    "ch110": 60.0,
    "ch111": 34990.0,
    "ch112": 32190.0,
    "ch113": 100.0,
    "ch114": 80.0,
    "ch115": 100.0,
    "ch116": 410.0,
    "ch117": 20500.0,
    "ch118": 30.0,
    "ch201": 16680.0,
    "ch202": 890.0,
    "ch203": 4750.0,
    "ch204": 15390.0,
    "ch205": 359400.0,
    "ch206": 1190.0,
    "ch207": 1540.0,
    "ch208": 1490.0,
    "ch209": 410.0
  },
  "coincidences": {}
}