{
  "timestamp": "2026-04-25T04:37:27.521917Z",
  "channels": {
    "ch101": 220.0,
    "ch102": 140.0,
    "ch103": 10.0,
    "ch104": 40.0,
    "ch105": 50.0,
    "ch106": 60.0,
    "ch107": 640.0,
    "ch108": 180.0,
    "ch109": 71210.0,
    "ch110": 70.0,
    "ch111": 35140.0,
    "ch112": 32840.0,
    "ch113": 140.0,
    "ch114": 90.0,
    "ch115": 180.0,
    "ch116": 230.0,
    "ch117": 22060.0,
    "ch118": 0.0,
    "ch201": 17010.0,
    "ch202": 1270.0,
    "ch203": 4400.0,
    "ch204": 14660.0,
    "ch205": 377860.0,
    "ch206": 2270.0,
    "ch207": 25450.0,
    "ch208": 5110.0,
    "ch209": 540.0
  },
  "coincidences": {}
}