{
  "timestamp": "2026-04-24T18:58:43.769255Z",
  "channels": {
    "ch101": 270.0,
    "ch102": 140.0,
    "ch103": 50.0,
    "ch104": 50.0,
    "ch105": 40.0,
    "ch106": 180.0,
    "ch107": 590.0,
    "ch108": 280.0,
    "ch109": 71790.0,
    "ch110": 70.0,
    "ch111": 33940.0,
    "ch112": 30600.0,
    "ch113": 140.0,
    "ch114": 90.0,
    "ch115": 370.0,
    "ch116": 230.0,
    "ch117": 22330.0,
    "ch118": 20.0,
    "ch201": 16940.0,
    "ch202": 1290.0,
    "ch203": 4460.0,
    "ch204": 12960.0,
    "ch205": 370660.0,
    "ch206": 10050.0,
    "ch207": 11390.0,
    "ch208": 1740.0,
    "ch209": 540.0
  },
  "coincidences": {}
}