{
  "timestamp": "2026-04-24T14:42:02.104158Z",
  "channels": {
    "ch101": 20.0,
    "ch102": 80.0,
    "ch103": 20.0,
    "ch104": 40.0,
    "ch105": 50.0,
    "ch106": 170.0,
    "ch107": 840.0,
    "ch108": 280.0,
    "ch109": 5030.0,
    "ch110": 170.0,
    "ch111": 33170.0,
    "ch112": 29770.0,
    "ch113": 180.0,
    "ch114": 70.0,
    "ch115": 170.0,
    "ch116": 220.0,
    "ch117": 20100.0,
    "ch118": 10.0,
    "ch201": 13260.0,
    "ch202": 990.0,
    "ch203": 360.0,
    "ch204": 30.0,
    "ch205": 374960.0,
    "ch206": 1710.0,
    "ch207": 1450.0,
    "ch208": 1630.0,
    "ch209": 660.0
  },
  "coincidences": {}
}