{
  "timestamp": "2026-04-26T11:00:10.994785Z",
  "channels": {
    "ch101": 290.0,
    "ch102": 130.0,
    "ch103": 40.0,
    "ch104": 40.0,
    "ch105": 20.0,
    "ch106": 120.0,
    "ch107": 890.0,
    "ch108": 230.0,
    "ch109": 72140.0,
    "ch110": 70.0,
    "ch111": 36540.0,
    "ch112": 32050.0,
    "ch113": 80.0,
    "ch114": 130.0,
    "ch115": 370.0,
    "ch116": 250.0,
    "ch117": 21250.0,
    "ch118": 10.0,
    "ch201": 17150.0,
    "ch202": 1220.0,
    "ch203": 310.0,
    "ch204": 640.0,
    "ch205": 352630.0,
    "ch206": 5240.0,
    "ch207": 2230.0,
    "ch208": 7860.0,
    "ch209": 590.0
  },
  "coincidences": {}
}