{
  "timestamp": "2026-04-24T18:00:14.384228Z",
  "channels": {
    "ch101": 270.0,
    "ch102": 200.0,
    "ch103": 0.0,
    "ch104": 30.0,
    "ch105": 20.0,
    "ch106": 130.0,
    "ch107": 1040.0,
    "ch108": 240.0,
    "ch109": 72090.0,
    "ch110": 70.0,
    "ch111": 34130.0,
    "ch112": 31410.0,
    "ch113": 200.0,
    "ch114": 80.0,
    "ch115": 270.0,
    "ch116": 300.0,
    "ch117": 22910.0,
    "ch118": 0.0,
    "ch201": 18350.0,
    "ch202": 940.0,
    "ch203": 4930.0,
    "ch204": 15150.0,
    "ch205": 376630.0,
    "ch206": 2150.0,
    "ch207": 13920.0,
    "ch208": 7000.0,
    "ch209": 500.0
  },
  "coincidences": {}
}