{
  "timestamp": "2026-04-26T02:01:50.099321Z",
  "channels": {
    "ch101": 180.0,
    "ch102": 120.0,
    "ch103": 30.0,
    "ch104": 40.0,
    "ch105": 20.0,
    "ch106": 110.0,
    "ch107": 520.0,
    "ch108": 180.0,
    "ch109": 72310.0,
    "ch110": 80.0,
    "ch111": 34320.0,
    "ch112": 31640.0,
    "ch113": 40.0,
    "ch114": 70.0,
    "ch115": 170.0,
    "ch116": 170.0,
    "ch117": 20740.0,
    "ch118": 20.0,
    "ch201": 15230.0,
    "ch202": 1100.0,
    "ch203": 200.0,
    "ch204": 610.0,
    "ch205": 345640.0,
    "ch206": 2050.0,
    "ch207": 25950.0,
    "ch208": 5320.0,
    "ch209": 470.0
  },
  "coincidences": {}
}