{
  "timestamp": "2026-04-26T07:00:32.184596Z",
  "channels": {
    "ch101": 240.0,
    "ch102": 140.0,
    "ch103": 20.0,
    "ch104": 60.0,
    "ch105": 20.0,
    "ch106": 140.0,
    "ch107": 610.0,
    "ch108": 220.0,
    "ch109": 70960.0,
    "ch110": 50.0,
    "ch111": 36230.0,
    "ch112": 32180.0,
    "ch113": 50.0,
    "ch114": 60.0,
    "ch115": 220.0,
    "ch116": 390.0,
    "ch117": 20140.0,
    "ch118": 0.0,
    "ch201": 16320.0,
    "ch202": 1310.0,
    "ch203": 280.0,
    "ch204": 660.0,
    "ch205": 358310.0,
    "ch206": 2310.0,
    "ch207": 24710.0,
    "ch208": 5430.0,
    "ch209": 500.0
  },
  "coincidences": {}
}