{
  "timestamp": "2026-04-24T19:47:52.380619Z",
  "channels": {
    "ch101": 250.0,
    "ch102": 200.0,
    "ch103": 40.0,
    "ch104": 30.0,
    "ch105": 30.0,
    "ch106": 160.0,
    "ch107": 710.0,
    "ch108": 210.0,
    "ch109": 70160.0,
    "ch110": 80.0,
    "ch111": 34770.0,
    "ch112": 32830.0,
    "ch113": 130.0,
    "ch114": 90.0,
    "ch115": 310.0,
    "ch116": 280.0,
    "ch117": 21500.0,
    "ch118": 10.0,
    "ch201": 17580.0,
    "ch202": 1520.0,
    "ch203": 5100.0,
    "ch204": 14220.0,
    "ch205": 377960.0,
    "ch206": 9910.0,
    "ch207": 11700.0,
    "ch208": 1810.0,
    "ch209": 450.0
  },
  "coincidences": {}
}