{
  "timestamp": "2026-04-27T07:53:52.231854Z",
  "channels": {
    "ch101": 20.0,
    "ch102": 40.0,
    "ch103": 20.0,
    "ch104": 20.0,
    "ch105": 40.0,
    "ch106": 70.0,
    "ch107": 790.0,
    "ch108": 160.0,
    "ch109": 20.0,
    "ch110": 20.0,
    "ch111": 35290.0,
    "ch112": 31730.0,
    "ch113": 30.0,
    "ch114": 80.0,
    "ch115": 190.0,
    "ch116": 220.0,
    "ch117": 19390.0,
    "ch118": 0.0,
    "ch201": 15760.0,
    "ch202": 1600.0,
    "ch203": 310.0,
    "ch204": 570.0,
    "ch205": 352540.0,
    "ch206": 1030.0,
    "ch207": 1390.0,
    "ch208": 1290.0,
    "ch209": 460.0
  },
  "coincidences": {}
}