{
  "timestamp": "2026-04-25T23:53:58.306800Z",
  "channels": {
    "ch101": 190.0,
    "ch102": 190.0,
    "ch103": 30.0,
    "ch104": 70.0,
    "ch105": 70.0,
    "ch106": 90.0,
    "ch107": 540.0,
    "ch108": 260.0,
    "ch109": 70440.0,
    "ch110": 40.0,
    "ch111": 34020.0,
    "ch112": 30350.0,
    "ch113": 110.0,
    "ch114": 70.0,
    "ch115": 430.0,
    "ch116": 290.0,
    "ch117": 21180.0,
    "ch118": 20.0,
    "ch201": 16980.0,
    "ch202": 1070.0,
    "ch203": 360.0,
    "ch204": 610.0,
    "ch205": 348110.0,
    "ch206": 2470.0,
    "ch207": 25750.0,
    "ch208": 5300.0,
    "ch209": 500.0
  },
  "coincidences": {}
}