{
  "timestamp": "2026-04-26T19:37:53.633110Z",
  "channels": {
    "ch101": 250.0,
    "ch102": 100.0,
    "ch103": 40.0,
    "ch104": 30.0,
    "ch105": 20.0,
    "ch106": 60.0,
    "ch107": 730.0,
    "ch108": 280.0,
    "ch109": 71860.0,
    "ch110": 60.0,
    "ch111": 37740.0,
    "ch112": 33350.0,
    "ch113": 90.0,
    "ch114": 40.0,
    "ch115": 200.0,
    "ch116": 300.0,
    "ch117": 21580.0,
    "ch118": 10.0,
    "ch201": 17000.0,
    "ch202": 1160.0,
    "ch203": 410.0,
    "ch204": 610.0,
    "ch205": 334330.0,
    "ch206": 1710.0,
    "ch207": 12650.0,
    "ch208": 7930.0,
    "ch209": 630.0
  },
  "coincidences": {}
}