{
  "timestamp": "2026-04-27T06:10:44.915062Z",
  "channels": {
    "ch101": 240.0,
    "ch102": 250.0,
    "ch103": 40.0,
    "ch104": 50.0,
    "ch105": 30.0,
    "ch106": 130.0,
    "ch107": 1130.0,
    "ch108": 200.0,
    "ch109": 70500.0,
    "ch110": 70.0,
    "ch111": 35910.0,
    "ch112": 31790.0,
    "ch113": 20.0,
    "ch114": 110.0,
    "ch115": 660.0,
    "ch116": 480.0,
    "ch117": 21260.0,
    "ch118": 20.0,
    "ch201": 16490.0,
    "ch202": 1380.0,
    "ch203": 240.0,
    "ch204": 690.0,
    "ch205": 352050.0,
    "ch206": 5430.0,
    "ch207": 2030.0,
    "ch208": 7550.0,
    "ch209": 570.0
  },
  "coincidences": {}
}