{
  "timestamp": "2026-04-26T00:09:45.215118Z",
  "channels": {
    "ch101": 180.0,
    "ch102": 100.0,
    "ch103": 40.0,
    "ch104": 40.0,
    "ch105": 30.0,
    "ch106": 170.0,
    "ch107": 680.0,
    "ch108": 210.0,
    "ch109": 69980.0,
    "ch110": 50.0,
    "ch111": 34120.0,
    "ch112": 30570.0,
    "ch113": 130.0,
    "ch114": 60.0,
    "ch115": 240.0,
    "ch116": 190.0,
    "ch117": 20920.0,
    "ch118": 0.0,
    "ch201": 15970.0,
    "ch202": 1030.0,
    "ch203": 310.0,
    "ch204": 580.0,
    "ch205": 346510.0,
    "ch206": 2700.0,
    "ch207": 26040.0,
    "ch208": 5640.0,
    "ch209": 490.0
  },
  "coincidences": {}
}