{
  "timestamp": "2026-04-26T02:09:08.832019Z",
  "channels": {
    "ch101": 280.0,
    "ch102": 160.0,
    "ch103": 70.0,
    "ch104": 40.0,
    "ch105": 10.0,
    "ch106": 90.0,
    "ch107": 540.0,
    "ch108": 180.0,
    "ch109": 71530.0,
    "ch110": 80.0,
    "ch111": 34060.0,
    "ch112": 31640.0,
    "ch113": 100.0,
    "ch114": 50.0,
    "ch115": 280.0,
    "ch116": 480.0,
    "ch117": 20270.0,
    "ch118": 10.0,
    "ch201": 16430.0,
    "ch202": 1040.0,
    "ch203": 330.0,
    "ch204": 590.0,
    "ch205": 343580.0,
    "ch206": 2520.0,
    "ch207": 24760.0,
    "ch208": 5360.0,
    "ch209": 450.0
  },
  "coincidences": {}
}