{
  "timestamp": "2026-04-27T09:02:31.342926Z",
  "channels": {
    "ch101": 50.0,
    "ch102": 50.0,
    "ch103": 10.0,
    "ch104": 50.0,
    "ch105": 10.0,
    "ch106": 110.0,
    "ch107": 1080.0,
    "ch108": 180.0,
    "ch109": 60.0,
    "ch110": 30.0,
    "ch111": 36650.0,
    "ch112": 32960.0,
    "ch113": 30.0,
    "ch114": 40.0,
    "ch115": 210.0,
    "ch116": 340.0,
    "ch117": 2720.0,
    "ch118": 0.0,
    "ch201": 3970.0,
    "ch202": 200.0,
    "ch203": 190.0,
    "ch204": 630.0,
    "ch205": 353640.0,
    "ch206": 720.0,
    "ch207": 1330.0,
    "ch208": 1220.0,
    "ch209": 450.0
  },
  "coincidences": {}
}