{
  "timestamp": "2026-04-26T21:53:39.742031Z",
  "channels": {
    "ch101": 170.0,
    "ch102": 180.0,
    "ch103": 30.0,
    "ch104": 20.0,
    "ch105": 30.0,
    "ch106": 140.0,
    "ch107": 780.0,
    "ch108": 210.0,
    "ch109": 71690.0,
    "ch110": 60.0,
    "ch111": 36590.0,
    "ch112": 32140.0,
    "ch113": 70.0,
    "ch114": 60.0,
    "ch115": 280.0,
    "ch116": 370.0,
    "ch117": 21610.0,
    "ch118": 40.0,
    "ch201": 17460.0,
    "ch202": 1370.0,
    "ch203": 230.0,
    "ch204": 630.0,
    "ch205": 341670.0,
    "ch206": 4320.0,
    "ch207": 4460.0,
    "ch208": 4110.0,
    "ch209": 490.0
  },
  "coincidences": {}
}