{
  "timestamp": "2026-04-24T21:03:00.054677Z",
  "channels": {
    "ch101": 200.0,
    "ch102": 210.0,
    "ch103": 20.0,
    "ch104": 40.0,
    "ch105": 40.0,
    "ch106": 250.0,
    "ch107": 1130.0,
    "ch108": 250.0,
    "ch109": 72830.0,
    "ch110": 70.0,
    "ch111": 33610.0,
    "ch112": 31680.0,
    "ch113": 80.0,
    "ch114": 120.0,
    "ch115": 390.0,
    "ch116": 350.0,
    "ch117": 23010.0,
    "ch118": 30.0,
    "ch201": 17650.0,
    "ch202": 1230.0,
    "ch203": 4760.0,
    "ch204": 14840.0,
    "ch205": 374650.0,
    "ch206": 2100.0,
    "ch207": 12840.0,
    "ch208": 8360.0,
    "ch209": 500.0
  },
  "coincidences": {}
}