{
  "timestamp": "2026-04-25T16:38:46.397044Z",
  "channels": {
    "ch101": 270.0,
    "ch102": 150.0,
    "ch103": 50.0,
    "ch104": 20.0,
    "ch105": 0.0,
    "ch106": 100.0,
    "ch107": 940.0,
    "ch108": 230.0,
    "ch109": 71830.0,
    "ch110": 140.0,
    "ch111": 35110.0,
    "ch112": 32610.0,
    "ch113": 90.0,
    "ch114": 80.0,
    "ch115": 140.0,
    "ch116": 320.0,
    "ch117": 20150.0,
    "ch118": 20.0,
    "ch201": 16260.0,
    "ch202": 940.0,
    "ch203": 290.0,
    "ch204": 570.0,
    "ch205": 359320.0,
    "ch206": 1050.0,
    "ch207": 1250.0,
    "ch208": 1670.0,
    "ch209": 440.0
  },
  "coincidences": {}
}