{
  "timestamp": "2026-04-27T01:12:40.425702Z",
  "channels": {
    "ch101": 300.0,
    "ch102": 100.0,
    "ch103": 20.0,
    "ch104": 40.0,
    "ch105": 10.0,
    "ch106": 150.0,
    "ch107": 1000.0,
    "ch108": 270.0,
    "ch109": 72470.0,
    "ch110": 30.0,
    "ch111": 35790.0,
    "ch112": 32050.0,
    "ch113": 70.0,
    "ch114": 40.0,
    "ch115": 430.0,
    "ch116": 540.0,
    "ch117": 21550.0,
    "ch118": 10.0,
    "ch201": 16530.0,
    "ch202": 1550.0,
    "ch203": 330.0,
    "ch204": 640.0,
    "ch205": 343490.0,
    "ch206": 4060.0,
    "ch207": 5310.0,
    "ch208": 4980.0,
    "ch209": 410.0
  },
  "coincidences": {}
}