{
  "timestamp": "2026-04-24T17:44:41.849748Z",
  "channels": {
    "ch101": 260.0,
    "ch102": 150.0,
    "ch103": 20.0,
    "ch104": 90.0,
    "ch105": 20.0,
    "ch106": 150.0,
    "ch107": 1490.0,
    "ch108": 350.0,
    "ch109": 71340.0,
    "ch110": 140.0,
    "ch111": 33330.0,
    "ch112": 31220.0,
    "ch113": 140.0,
    "ch114": 50.0,
    "ch115": 340.0,
    "ch116": 270.0,
    "ch117": 22870.0,
    "ch118": 0.0,
    "ch201": 18380.0,
    "ch202": 710.0,
    "ch203": 5380.0,
    "ch204": 15910.0,
    "ch205": 372310.0,
    "ch206": 2000.0,
    "ch207": 13750.0,
    "ch208": 6900.0,
    "ch209": 490.0
  },
  "coincidences": {}
}