{
  "timestamp": "2026-04-27T07:00:42.259597Z",
  "channels": {
    "ch101": 290.0,
    "ch102": 120.0,
    "ch103": 70.0,
    "ch104": 10.0,
    "ch105": 30.0,
    "ch106": 70.0,
    "ch107": 1030.0,
    "ch108": 150.0,
    "ch109": 71020.0,
    "ch110": 30.0,
    "ch111": 36020.0,
    "ch112": 31500.0,
    "ch113": 50.0,
    "ch114": 80.0,
    "ch115": 130.0,
    "ch116": 330.0,
    "ch117": 20170.0,
    "ch118": 0.0,
    "ch201": 16370.0,
    "ch202": 1520.0,
    "ch203": 250.0,
    "ch204": 600.0,
    "ch205": 349640.0,
    "ch206": 4930.0,
    "ch207": 2080.0,
    "ch208": 7680.0,
    "ch209": 370.0
  },
  "coincidences": {}
}