{
  "timestamp": "2026-04-26T06:34:53.413725Z",
  "channels": {
    "ch101": 170.0,
    "ch102": 170.0,
    "ch103": 0.0,
    "ch104": 90.0,
    "ch105": 30.0,
    "ch106": 110.0,
    "ch107": 390.0,
    "ch108": 250.0,
    "ch109": 70520.0,
    "ch110": 70.0,
    "ch111": 36000.0,
    "ch112": 32360.0,
    "ch113": 90.0,
    "ch114": 50.0,
    "ch115": 190.0,
    "ch116": 190.0,
    "ch117": 20220.0,
    "ch118": 0.0,
    "ch201": 16850.0,
    "ch202": 1260.0,
    "ch203": 340.0,
    "ch204": 610.0,
    "ch205": 356630.0,
    "ch206": 2370.0,
    "ch207": 25130.0,
    "ch208": 5860.0,
    "ch209": 500.0
  },
  "coincidences": {}
}