{
  "timestamp": "2026-04-27T00:16:16.686861Z",
  "channels": {
    "ch101": 250.0,
    "ch102": 120.0,
    "ch103": 50.0,
    "ch104": 50.0,
    "ch105": 40.0,
    "ch106": 180.0,
    "ch107": 1070.0,
    "ch108": 350.0,
    "ch109": 71470.0,
    "ch110": 40.0,
    "ch111": 36200.0,
    "ch112": 31280.0,
    "ch113": 100.0,
    "ch114": 50.0,
    "ch115": 200.0,
    "ch116": 320.0,
    "ch117": 21500.0,
    "ch118": 10.0,
    "ch201": 16440.0,
    "ch202": 1450.0,
    "ch203": 300.0,
    "ch204": 560.0,
    "ch205": 341010.0,
    "ch206": 2330.0,
    "ch207": 25560.0,
    "ch208": 5680.0,
    "ch209": 440.0
  },
  "coincidences": {}
}