{
  "timestamp": "2026-04-27T10:45:53.945674Z",
  "channels": {
    "ch101": 1870.0,
    "ch102": 1490.0,
    "ch103": 10.0,
    "ch104": 40.0,
    "ch105": 40.0,
    "ch106": 160.0,
    "ch107": 1170.0,
    "ch108": 340.0,
    "ch109": 90.0,
    "ch110": 20.0,
    "ch111": 40.0,
    "ch112": 50.0,
    "ch113": 50.0,
    "ch114": 70.0,
    "ch115": 220.0,
    "ch116": 490.0,
    "ch117": 2380.0,
    "ch118": 10.0,
    "ch201": 4090.0,
    "ch202": 190.0,
    "ch203": 360.0,
    "ch204": 720.0,
    "ch205": 356840.0,
    "ch206": 970.0,
    "ch207": 1450.0,
    "ch208": 1540.0,
    "ch209": 790.0
  },
  "coincidences": {}
}