{
  "timestamp": "2026-04-25T23:11:09.479053Z",
  "channels": {
    "ch101": 250.0,
    "ch102": 90.0,
    "ch103": 20.0,
    "ch104": 40.0,
    "ch105": 30.0,
    "ch106": 190.0,
    "ch107": 890.0,
    "ch108": 240.0,
    "ch109": 72080.0,
    "ch110": 70.0,
    "ch111": 33830.0,
    "ch112": 31030.0,
    "ch113": 80.0,
    "ch114": 110.0,
    "ch115": 310.0,
    "ch116": 540.0,
    "ch117": 20530.0,
    "ch118": 30.0,
    "ch201": 15880.0,
    "ch202": 1080.0,
    "ch203": 260.0,
    "ch204": 660.0,
    "ch205": 350840.0,
    "ch206": 2590.0,
    "ch207": 24410.0,
    "ch208": 5340.0,
    "ch209": 550.0
  },
  "coincidences": {}
}