{
  "timestamp": "2026-04-24T22:43:08.725394Z",
  "channels": {
    "ch101": 290.0,
    "ch102": 180.0,
    "ch103": 50.0,
    "ch104": 20.0,
    "ch105": 10.0,
    "ch106": 100.0,
    "ch107": 780.0,
    "ch108": 380.0,
    "ch109": 72640.0,
    "ch110": 80.0,
    "ch111": 33520.0,
    "ch112": 33160.0,
    "ch113": 130.0,
    "ch114": 70.0,
    "ch115": 330.0,
    "ch116": 450.0,
    "ch117": 22690.0,
    "ch118": 20.0,
    "ch201": 17150.0,
    "ch202": 960.0,
    "ch203": 4660.0,
    "ch204": 15520.0,
    "ch205": 376400.0,
    "ch206": 2580.0,
    "ch207": 25070.0,
    "ch208": 5630.0,
    "ch209": 510.0
  },
  "coincidences": {}
}