{
  "timestamp": "2026-04-26T08:44:00.899768Z",
  "channels": {
    "ch101": 340.0,
    "ch102": 190.0,
    "ch103": 40.0,
    "ch104": 60.0,
    "ch105": 20.0,
    "ch106": 150.0,
    "ch107": 580.0,
    "ch108": 150.0,
    "ch109": 71920.0,
    "ch110": 70.0,
    "ch111": 34790.0,
    "ch112": 31350.0,
    "ch113": 110.0,
    "ch114": 60.0,
    "ch115": 190.0,
    "ch116": 360.0,
    "ch117": 20730.0,
    "ch118": 0.0,
    "ch201": 17370.0,
    "ch202": 1240.0,
    "ch203": 220.0,
    "ch204": 720.0,
    "ch205": 359300.0,
    "ch206": 5390.0,
    "ch207": 1940.0,
    "ch208": 7590.0,
    "ch209": 590.0
  },
  "coincidences": {}
}