{
  "timestamp": "2026-04-26T10:40:00.162546Z",
  "channels": {
    "ch101": 230.0,
    "ch102": 90.0,
    "ch103": 50.0,
    "ch104": 40.0,
    "ch105": 50.0,
    "ch106": 110.0,
    "ch107": 780.0,
    "ch108": 240.0,
    "ch109": 71620.0,
    "ch110": 80.0,
    "ch111": 35420.0,
    "ch112": 31580.0,
    "ch113": 80.0,
    "ch114": 80.0,
    "ch115": 180.0,
    "ch116": 260.0,
    "ch117": 21520.0,
    "ch118": 0.0,
    "ch201": 16440.0,
    "ch202": 1050.0,
    "ch203": 200.0,
    "ch204": 580.0,
    "ch205": 354940.0,
    "ch206": 5400.0,
    "ch207": 1730.0,
    "ch208": 7850.0,
    "ch209": 460.0
  },
  "coincidences": {}
}