{
  "timestamp": "2026-04-26T04:35:08.434192Z",
  "channels": {
    "ch101": 310.0,
    "ch102": 90.0,
    "ch103": 0.0,
    "ch104": 10.0,
    "ch105": 10.0,
    "ch106": 200.0,
    "ch107": 900.0,
    "ch108": 230.0,
    "ch109": 70770.0,
    "ch110": 70.0,
    "ch111": 33640.0,
    "ch112": 31030.0,
    "ch113": 50.0,
    "ch114": 50.0,
    "ch115": 230.0,
    "ch116": 290.0,
    "ch117": 20610.0,
    "ch118": 10.0,
    "ch201": 16470.0,
    "ch202": 1180.0,
    "ch203": 220.0,
    "ch204": 690.0,
    "ch205": 349260.0,
    "ch206": 2390.0,
    "ch207": 26490.0,
    "ch208": 5480.0,
    "ch209": 450.0
  },
  "coincidences": {}
}