{
  "timestamp": "2026-04-26T21:25:51.254187Z",
  "channels": {
    "ch101": 170.0,
    "ch102": 130.0,
    "ch103": 60.0,
    "ch104": 20.0,
    "ch105": 40.0,
    "ch106": 170.0,
    "ch107": 920.0,
    "ch108": 240.0,
    "ch109": 71500.0,
    "ch110": 70.0,
    "ch111": 36330.0,
    "ch112": 31400.0,
    "ch113": 110.0,
    "ch114": 60.0,
    "ch115": 200.0,
    "ch116": 270.0,
    "ch117": 22380.0,
    "ch118": 10.0,
    "ch201": 17100.0,
    "ch202": 1190.0,
    "ch203": 220.0,
    "ch204": 560.0,
    "ch205": 343690.0,
    "ch206": 2780.0,
    "ch207": 25620.0,
    "ch208": 4680.0,
    "ch209": 480.0
  },
  "coincidences": {}
}