{
  "timestamp": "2026-04-26T18:38:13.797963Z",
  "channels": {
    "ch101": 160.0,
    "ch102": 130.0,
    "ch103": 10.0,
    "ch104": 30.0,
    "ch105": 60.0,
    "ch106": 150.0,
    "ch107": 1040.0,
    "ch108": 300.0,
    "ch109": 71430.0,
    "ch110": 50.0,
    "ch111": 36270.0,
    "ch112": 32750.0,
    "ch113": 130.0,
    "ch114": 60.0,
    "ch115": 340.0,
    "ch116": 250.0,
    "ch117": 21940.0,
    "ch118": 0.0,
    "ch201": 16190.0,
    "ch202": 880.0,
    "ch203": 270.0,
    "ch204": 550.0,
    "ch205": 343160.0,
    "ch206": 1480.0,
    "ch207": 12980.0,
    "ch208": 8110.0,
    "ch209": 470.0
  },
  "coincidences": {}
}