{
  "timestamp": "2026-04-26T08:04:43.596162Z",
  "channels": {
    "ch101": 150.0,
    "ch102": 170.0,
    "ch103": 20.0,
    "ch104": 70.0,
    "ch105": 10.0,
    "ch106": 130.0,
    "ch107": 810.0,
    "ch108": 220.0,
    "ch109": 70980.0,
    "ch110": 100.0,
    "ch111": 34830.0,
    "ch112": 31670.0,
    "ch113": 140.0,
    "ch114": 100.0,
    "ch115": 320.0,
    "ch116": 400.0,
    "ch117": 22330.0,
    "ch118": 10.0,
    "ch201": 18140.0,
    "ch202": 1130.0,
    "ch203": 410.0,
    "ch204": 790.0,
    "ch205": 351620.0,
    "ch206": 4960.0,
    "ch207": 1690.0,
    "ch208": 7730.0,
    "ch209": 450.0
  },
  "coincidences": {}
}