{
  "timestamp": "2026-04-26T08:33:56.542411Z",
  "channels": {
    "ch101": 290.0,
    "ch102": 130.0,
    "ch103": 30.0,
    "ch104": 40.0,
    "ch105": 40.0,
    "ch106": 160.0,
    "ch107": 840.0,
    "ch108": 340.0,
    "ch109": 69520.0,
    "ch110": 70.0,
    "ch111": 33420.0,
    "ch112": 31610.0,
    "ch113": 50.0,
    "ch114": 70.0,
    "ch115": 410.0,
    "ch116": 280.0,
    "ch117": 20080.0,
    "ch118": 20.0,
    "ch201": 16120.0,
    "ch202": 1510.0,
    "ch203": 240.0,
    "ch204": 760.0,
    "ch205": 360980.0,
    "ch206": 4910.0,
    "ch207": 2030.0,
    "ch208": 7510.0,
    "ch209": 410.0
  },
  "coincidences": {}
}