{
  "timestamp": "2026-04-25T17:41:13.259323Z",
  "channels": {
    "ch101": 290.0,
    "ch102": 160.0,
    "ch103": 30.0,
    "ch104": 10.0,
    "ch105": 20.0,
    "ch106": 130.0,
    "ch107": 850.0,
    "ch108": 250.0,
    "ch109": 70840.0,
    "ch110": 120.0,
    "ch111": 34580.0,
    "ch112": 32570.0,
    "ch113": 140.0,
    "ch114": 40.0,
    "ch115": 260.0,
    "ch116": 290.0,
    "ch117": 20100.0,
    "ch118": 0.0,
    "ch201": 16340.0,
    "ch202": 760.0,
    "ch203": 350.0,
    "ch204": 660.0,
    "ch205": 361560.0,
    "ch206": 1240.0,
    "ch207": 1160.0,
    "ch208": 1300.0,
    "ch209": 600.0
  },
  "coincidences": {}
}