{
  "timestamp": "2026-04-25T09:40:42.213000Z",
  "channels": {
    "ch101": 280.0,
    "ch102": 120.0,
    "ch103": 40.0,
    "ch104": 20.0,
    "ch105": 20.0,
    "ch106": 180.0,
    "ch107": 890.0,
    "ch108": 270.0,
    "ch109": 70660.0,
    "ch110": 60.0,
    "ch111": 35570.0,
    "ch112": 32790.0,
    "ch113": 130.0,
    "ch114": 70.0,
    "ch115": 240.0,
    "ch116": 350.0,
    "ch117": 22420.0,
    "ch118": 10.0,
    "ch201": 17830.0,
    "ch202": 1400.0,
    "ch203": 4510.0,
    "ch204": 13950.0,
    "ch205": 384930.0,
    "ch206": 4100.0,
    "ch207": 4240.0,
    "ch208": 4320.0,
    "ch209": 480.0
  },
  "coincidences": {}
}