{
  "timestamp": "2026-04-27T03:09:19.748265Z",
  "channels": {
    "ch101": 200.0,
    "ch102": 150.0,
    "ch103": 20.0,
    "ch104": 60.0,
    "ch105": 40.0,
    "ch106": 150.0,
    "ch107": 810.0,
    "ch108": 220.0,
    "ch109": 71640.0,
    "ch110": 50.0,
    "ch111": 33340.0,
    "ch112": 30470.0,
    "ch113": 130.0,
    "ch114": 70.0,
    "ch115": 210.0,
    "ch116": 360.0,
    "ch117": 20760.0,
    "ch118": 0.0,
    "ch201": 16310.0,
    "ch202": 1610.0,
    "ch203": 240.0,
    "ch204": 700.0,
    "ch205": 338710.0,
    "ch206": 1750.0,
    "ch207": 12250.0,
    "ch208": 8290.0,
    "ch209": 350.0
  },
  "coincidences": {}
}