{
  "timestamp": "2026-04-26T10:50:53.870421Z",
  "channels": {
    "ch101": 330.0,
    "ch102": 200.0,
    "ch103": 10.0,
    "ch104": 50.0,
    "ch105": 20.0,
    "ch106": 100.0,
    "ch107": 640.0,
    "ch108": 240.0,
    "ch109": 70390.0,
    "ch110": 40.0,
    "ch111": 34630.0,
    "ch112": 32100.0,
    "ch113": 120.0,
    "ch114": 80.0,
    "ch115": 150.0,
    "ch116": 240.0,
    "ch117": 21820.0,
    "ch118": 0.0,
    "ch201": 16990.0,
    "ch202": 1260.0,
    "ch203": 230.0,
    "ch204": 680.0,
    "ch205": 357530.0,
    "ch206": 5030.0,
    "ch207": 1780.0,
    "ch208": 8000.0,
    "ch209": 610.0
  },
  "coincidences": {}
}