{
  "timestamp": "2026-04-24T18:20:42.340300Z",
  "channels": {
    "ch101": 290.0,
    "ch102": 110.0,
    "ch103": 20.0,
    "ch104": 60.0,
    "ch105": 50.0,
    "ch106": 130.0,
    "ch107": 780.0,
    "ch108": 220.0,
    "ch109": 71560.0,
    "ch110": 90.0,
    "ch111": 35120.0,
    "ch112": 30830.0,
    "ch113": 150.0,
    "ch114": 120.0,
    "ch115": 160.0,
    "ch116": 320.0,
    "ch117": 22150.0,
    "ch118": 10.0,
    "ch201": 16630.0,
    "ch202": 1000.0,
    "ch203": 4760.0,
    "ch204": 15330.0,
    "ch205": 364080.0,
    "ch206": 9890.0,
    "ch207": 11300.0,
    "ch208": 1290.0,
    "ch209": 340.0
  },
  "coincidences": {}
}