{
  "timestamp": "2026-04-26T21:50:18.966348Z",
  "channels": {
    "ch101": 230.0,
    "ch102": 170.0,
    "ch103": 40.0,
    "ch104": 70.0,
    "ch105": 10.0,
    "ch106": 200.0,
    "ch107": 980.0,
    "ch108": 330.0,
    "ch109": 69750.0,
    "ch110": 40.0,
    "ch111": 35990.0,
    "ch112": 32000.0,
    "ch113": 90.0,
    "ch114": 70.0,
    "ch115": 240.0,
    "ch116": 340.0,
    "ch117": 21220.0,
    "ch118": 20.0,
    "ch201": 16000.0,
    "ch202": 1720.0,
    "ch203": 180.0,
    "ch204": 600.0,
    "ch205": 337350.0,
    "ch206": 3730.0,
    "ch207": 5470.0,
    "ch208": 4740.0,
    "ch209": 480.0
  },
  "coincidences": {}
}