{
  "timestamp": "2026-04-27T04:55:42.701544Z",
  "channels": {
    "ch101": 300.0,
    "ch102": 140.0,
    "ch103": 20.0,
    "ch104": 60.0,
    "ch105": 20.0,
    "ch106": 170.0,
    "ch107": 1200.0,
    "ch108": 230.0,
    "ch109": 72340.0,
    "ch110": 70.0,
    "ch111": 33970.0,
    "ch112": 30670.0,
    "ch113": 130.0,
    "ch114": 60.0,
    "ch115": 220.0,
    "ch116": 230.0,
    "ch117": 20720.0,
    "ch118": 30.0,
    "ch201": 16460.0,
    "ch202": 1410.0,
    "ch203": 290.0,
    "ch204": 610.0,
    "ch205": 343730.0,
    "ch206": 1000.0,
    "ch207": 1300.0,
    "ch208": 1490.0,
    "ch209": 440.0
  },
  "coincidences": {}
}