{
  "timestamp": "2026-04-25T12:12:29.338708Z",
  "channels": {
    "ch101": 300.0,
    "ch102": 180.0,
    "ch103": 50.0,
    "ch104": 10.0,
    "ch105": 40.0,
    "ch106": 150.0,
    "ch107": 770.0,
    "ch108": 260.0,
    "ch109": 70950.0,
    "ch110": 40.0,
    "ch111": 35360.0,
    "ch112": 32860.0,
    "ch113": 140.0,
    "ch114": 80.0,
    "ch115": 190.0,
    "ch116": 220.0,
    "ch117": 21990.0,
    "ch118": 20.0,
    "ch201": 17490.0,
    "ch202": 920.0,
    "ch203": 4740.0,
    "ch204": 15390.0,
    "ch205": 377850.0,
    "ch206": 920.0,
    "ch207": 1200.0,
    "ch208": 1070.0,
    "ch209": 420.0
  },
  "coincidences": {}
}