{
  "timestamp": "2026-04-24T20:29:50.873738Z",
  "channels": {
    "ch101": 220.0,
    "ch102": 130.0,
    "ch103": 30.0,
    "ch104": 40.0,
    "ch105": 10.0,
    "ch106": 140.0,
    "ch107": 860.0,
    "ch108": 230.0,
    "ch109": 72840.0,
    "ch110": 140.0,
    "ch111": 34130.0,
    "ch112": 31530.0,
    "ch113": 130.0,
    "ch114": 50.0,
    "ch115": 330.0,
    "ch116": 240.0,
    "ch117": 23340.0,
    "ch118": 10.0,
    "ch201": 17880.0,
    "ch202": 1130.0,
    "ch203": 4860.0,
    "ch204": 14970.0,
    "ch205": 376920.0,
    "ch206": 9770.0,
    "ch207": 12260.0,
    "ch208": 1600.0,
    "ch209": 380.0
  },
  "coincidences": {}
}