{
  "timestamp": "2026-04-26T17:14:36.227982Z",
  "channels": {
    "ch101": 320.0,
    "ch102": 110.0,
    "ch103": 20.0,
    "ch104": 80.0,
    "ch105": 60.0,
    "ch106": 100.0,
    "ch107": 700.0,
    "ch108": 220.0,
    "ch109": 70560.0,
    "ch110": 90.0,
    "ch111": 36160.0,
    "ch112": 32860.0,
    "ch113": 110.0,
    "ch114": 110.0,
    "ch115": 170.0,
    "ch116": 380.0,
    "ch117": 21230.0,
    "ch118": 10.0,
    "ch201": 16610.0,
    "ch202": 850.0,
    "ch203": 400.0,
    "ch204": 640.0,
    "ch205": 349580.0,
    "ch206": 5010.0,
    "ch207": 2040.0,
    "ch208": 7310.0,
    "ch209": 570.0
  },
  "coincidences": {}
}