{
  "timestamp": "2026-04-26T10:33:04.762584Z",
  "channels": {
    "ch101": 260.0,
    "ch102": 120.0,
    "ch103": 60.0,
    "ch104": 40.0,
    "ch105": 10.0,
    "ch106": 280.0,
    "ch107": 750.0,
    "ch108": 290.0,
    "ch109": 71610.0,
    "ch110": 60.0,
    "ch111": 35740.0,
    "ch112": 32130.0,
    "ch113": 130.0,
    "ch114": 70.0,
    "ch115": 300.0,
    "ch116": 390.0,
    "ch117": 21480.0,
    "ch118": 10.0,
    "ch201": 16790.0,
    "ch202": 1510.0,
    "ch203": 340.0,
    "ch204": 550.0,
    "ch205": 357930.0,
    "ch206": 4650.0,
    "ch207": 1800.0,
    "ch208": 7620.0,
    "ch209": 380.0
  },
  "coincidences": {}
}