{
  "timestamp": "2026-04-25T05:20:24.343518Z",
  "channels": {
    "ch101": 230.0,
    "ch102": 140.0,
    "ch103": 30.0,
    "ch104": 20.0,
    "ch105": 30.0,
    "ch106": 100.0,
    "ch107": 600.0,
    "ch108": 250.0,
    "ch109": 71400.0,
    "ch110": 160.0,
    "ch111": 35030.0,
    "ch112": 31710.0,
    "ch113": 70.0,
    "ch114": 80.0,
    "ch115": 230.0,
    "ch116": 350.0,
    "ch117": 21230.0,
    "ch118": 10.0,
    "ch201": 15900.0,
    "ch202": 1720.0,
    "ch203": 4530.0,
    "ch204": 14510.0,
    "ch205": 378000.0,
    "ch206": 2460.0,
    "ch207": 25300.0,
    "ch208": 5390.0,
    "ch209": 540.0
  },
  "coincidences": {}
}