{
  "timestamp": "2026-04-26T00:57:06.479182Z",
  "channels": {
    "ch101": 220.0,
    "ch102": 110.0,
    "ch103": 20.0,
    "ch104": 10.0,
    "ch105": 40.0,
    "ch106": 100.0,
    "ch107": 590.0,
    "ch108": 240.0,
    "ch109": 70740.0,
    "ch110": 40.0,
    "ch111": 34010.0,
    "ch112": 29750.0,
    "ch113": 110.0,
    "ch114": 60.0,
    "ch115": 350.0,
    "ch116": 250.0,
    "ch117": 21400.0,
    "ch118": 10.0,
    "ch201": 16210.0,
    "ch202": 920.0,
    "ch203": 350.0,
    "ch204": 560.0,
    "ch205": 354240.0,
    "ch206": 2520.0,
    "ch207": 26430.0,
    "ch208": 5680.0,
    "ch209": 490.0
  },
  "coincidences": {}
}