{
  "timestamp": "2026-04-27T07:10:13.946310Z",
  "channels": {
    "ch101": 20.0,
    "ch102": 50.0,
    "ch103": 40.0,
    "ch104": 20.0,
    "ch105": 10.0,
    "ch106": 40.0,
    "ch107": 1490.0,
    "ch108": 210.0,
    "ch109": 20.0,
    "ch110": 50.0,
    "ch111": 35280.0,
    "ch112": 31290.0,
    "ch113": 100.0,
    "ch114": 20.0,
    "ch115": 260.0,
    "ch116": 290.0,
    "ch117": 19830.0,
    "ch118": 0.0,
    "ch201": 15620.0,
    "ch202": 1570.0,
    "ch203": 230.0,
    "ch204": 620.0,
    "ch205": 351150.0,
    "ch206": 1060.0,
    "ch207": 1130.0,
    "ch208": 1550.0,
    "ch209": 400.0
  },
  "coincidences": {}
}