{
  "timestamp": "2026-04-27T06:52:34.722872Z",
  "channels": {
    "ch101": 260.0,
    "ch102": 180.0,
    "ch103": 30.0,
    "ch104": 20.0,
    "ch105": 10.0,
    "ch106": 100.0,
    "ch107": 940.0,
    "ch108": 150.0,
    "ch109": 69990.0,
    "ch110": 80.0,
    "ch111": 35250.0,
    "ch112": 31780.0,
    "ch113": 100.0,
    "ch114": 50.0,
    "ch115": 390.0,
    "ch116": 220.0,
    "ch117": 21010.0,
    "ch118": 40.0,
    "ch201": 16530.0,
    "ch202": 1640.0,
    "ch203": 310.0,
    "ch204": 620.0,
    "ch205": 355540.0,
    "ch206": 5330.0,
    "ch207": 2030.0,
    "ch208": 7650.0,
    "ch209": 450.0
  },
  "coincidences": {}
}