{
  "timestamp": "2026-04-25T16:34:17.636476Z",
  "channels": {
    "ch101": 170.0,
    "ch102": 110.0,
    "ch103": 30.0,
    "ch104": 40.0,
    "ch105": 50.0,
    "ch106": 80.0,
    "ch107": 700.0,
    "ch108": 280.0,
    "ch109": 71130.0,
    "ch110": 70.0,
    "ch111": 35510.0,
    "ch112": 33330.0,
    "ch113": 120.0,
    "ch114": 70.0,
    "ch115": 150.0,
    "ch116": 360.0,
    "ch117": 20960.0,
    "ch118": 20.0,
    "ch201": 16330.0,
    "ch202": 750.0,
    "ch203": 310.0,
    "ch204": 750.0,
    "ch205": 362120.0,
    "ch206": 990.0,
    "ch207": 1060.0,
    "ch208": 1510.0,
    "ch209": 430.0
  },
  "coincidences": {}
}