{
  "timestamp": "2026-04-27T03:33:14.072684Z",
  "channels": {
    "ch101": 150.0,
    "ch102": 130.0,
    "ch103": 20.0,
    "ch104": 40.0,
    "ch105": 30.0,
    "ch106": 140.0,
    "ch107": 660.0,
    "ch108": 180.0,
    "ch109": 71610.0,
    "ch110": 110.0,
    "ch111": 33080.0,
    "ch112": 30710.0,
    "ch113": 40.0,
    "ch114": 50.0,
    "ch115": 160.0,
    "ch116": 150.0,
    "ch117": 20450.0,
    "ch118": 10.0,
    "ch201": 15830.0,
    "ch202": 1430.0,
    "ch203": 270.0,
    "ch204": 510.0,
    "ch205": 334550.0,
    "ch206": 10560.0,
    "ch207": 11070.0,
    "ch208": 1780.0,
    "ch209": 570.0
  },
  "coincidences": {}
}