{
  "timestamp": "2026-04-26T08:50:19.110812Z",
  "channels": {
    "ch101": 250.0,
    "ch102": 190.0,
    "ch103": 30.0,
    "ch104": 10.0,
    "ch105": 70.0,
    "ch106": 230.0,
    "ch107": 630.0,
    "ch108": 220.0,
    "ch109": 70520.0,
    "ch110": 100.0,
    "ch111": 34770.0,
    "ch112": 31650.0,
    "ch113": 120.0,
    "ch114": 90.0,
    "ch115": 310.0,
    "ch116": 390.0,
    "ch117": 21210.0,
    "ch118": 20.0,
    "ch201": 16610.0,
    "ch202": 1350.0,
    "ch203": 240.0,
    "ch204": 590.0,
    "ch205": 359720.0,
    "ch206": 4630.0,
    "ch207": 2040.0,
    "ch208": 7860.0,
    "ch209": 580.0
  },
  "coincidences": {}
}