{
  "timestamp": "2026-04-26T05:58:00.950587Z",
  "channels": {
    "ch101": 280.0,
    "ch102": 200.0,
    "ch103": 50.0,
    "ch104": 40.0,
    "ch105": 20.0,
    "ch106": 120.0,
    "ch107": 530.0,
    "ch108": 220.0,
    "ch109": 71730.0,
    "ch110": 50.0,
    "ch111": 35520.0,
    "ch112": 31930.0,
    "ch113": 100.0,
    "ch114": 50.0,
    "ch115": 280.0,
    "ch116": 230.0,
    "ch117": 20970.0,
    "ch118": 10.0,
    "ch201": 16310.0,
    "ch202": 1330.0,
    "ch203": 250.0,
    "ch204": 620.0,
    "ch205": 355590.0,
    "ch206": 2220.0,
    "ch207": 24520.0,
    "ch208": 4970.0,
    "ch209": 630.0
  },
  "coincidences": {}
}