{
  "timestamp": "2026-04-26T02:25:08.722073Z",
  "channels": {
    "ch101": 260.0,
    "ch102": 190.0,
    "ch103": 20.0,
    "ch104": 50.0,
    "ch105": 30.0,
    "ch106": 100.0,
    "ch107": 650.0,
    "ch108": 300.0,
    "ch109": 71920.0,
    "ch110": 130.0,
    "ch111": 34400.0,
    "ch112": 32520.0,
    "ch113": 150.0,
    "ch114": 90.0,
    "ch115": 200.0,
    "ch116": 230.0,
    "ch117": 20820.0,
    "ch118": 0.0,
    "ch201": 16830.0,
    "ch202": 960.0,
    "ch203": 220.0,
    "ch204": 720.0,
    "ch205": 351600.0,
    "ch206": 2710.0,
    "ch207": 24970.0,
    "ch208": 5570.0,
    "ch209": 570.0
  },
  "coincidences": {}
}