{
  "timestamp": "2026-04-25T02:44:19.082463Z",
  "channels": {
    "ch101": 240.0,
    "ch102": 100.0,
    "ch103": 20.0,
    "ch104": 40.0,
    "ch105": 10.0,
    "ch106": 110.0,
    "ch107": 750.0,
    "ch108": 210.0,
    "ch109": 73140.0,
    "ch110": 100.0,
    "ch111": 34310.0,
    "ch112": 32300.0,
    "ch113": 110.0,
    "ch114": 50.0,
    "ch115": 330.0,
    "ch116": 300.0,
    "ch117": 24050.0,
    "ch118": 20.0,
    "ch201": 18260.0,
    "ch202": 1200.0,
    "ch203": 4970.0,
    "ch204": 14710.0,
    "ch205": 376500.0,
    "ch206": 2430.0,
    "ch207": 25860.0,
    "ch208": 5310.0,
    "ch209": 520.0
  },
  "coincidences": {}
}