{
  "timestamp": "2026-04-26T07:00:55.928158Z",
  "channels": {
    "ch101": 270.0,
    "ch102": 190.0,
    "ch103": 60.0,
    "ch104": 40.0,
    "ch105": 40.0,
    "ch106": 160.0,
    "ch107": 520.0,
    "ch108": 230.0,
    "ch109": 71010.0,
    "ch110": 100.0,
    "ch111": 35110.0,
    "ch112": 33470.0,
    "ch113": 60.0,
    "ch114": 100.0,
    "ch115": 230.0,
    "ch116": 440.0,
    "ch117": 20760.0,
    "ch118": 40.0,
    "ch201": 16080.0,
    "ch202": 1520.0,
    "ch203": 320.0,
    "ch204": 730.0,
    "ch205": 357110.0,
    "ch206": 2670.0,
    "ch207": 24700.0,
    "ch208": 5770.0,
    "ch209": 530.0
  },
  "coincidences": {}
}