{
  "timestamp": "2026-04-24T22:11:59.075966Z",
  "channels": {
    "ch101": 190.0,
    "ch102": 130.0,
    "ch103": 20.0,
    "ch104": 30.0,
    "ch105": 30.0,
    "ch106": 190.0,
    "ch107": 820.0,
    "ch108": 260.0,
    "ch109": 73560.0,
    "ch110": 70.0,
    "ch111": 32800.0,
    "ch112": 31130.0,
    "ch113": 100.0,
    "ch114": 70.0,
    "ch115": 340.0,
    "ch116": 260.0,
    "ch117": 22780.0,
    "ch118": 0.0,
    "ch201": 18710.0,
    "ch202": 1430.0,
    "ch203": 4870.0,
    "ch204": 14960.0,
    "ch205": 378690.0,
    "ch206": 2460.0,
    "ch207": 26270.0,
    "ch208": 4890.0,
    "ch209": 380.0
  },
  "coincidences": {}
}