{
  "timestamp": "2026-04-26T01:43:53.279826Z",
  "channels": {
    "ch101": 220.0,
    "ch102": 180.0,
    "ch103": 10.0,
    "ch104": 60.0,
    "ch105": 40.0,
    "ch106": 100.0,
    "ch107": 480.0,
    "ch108": 200.0,
    "ch109": 73140.0,
    "ch110": 30.0,
    "ch111": 33350.0,
    "ch112": 31350.0,
    "ch113": 70.0,
    "ch114": 100.0,
    "ch115": 180.0,
    "ch116": 200.0,
    "ch117": 21340.0,
    "ch118": 0.0,
    "ch201": 16210.0,
    "ch202": 970.0,
    "ch203": 230.0,
    "ch204": 510.0,
    "ch205": 353460.0,
    "ch206": 2590.0,
    "ch207": 25640.0,
    "ch208": 4950.0,
    "ch209": 600.0
  },
  "coincidences": {}
}