{
  "timestamp": "2026-04-25T04:21:07.223866Z",
  "channels": {
    "ch101": 280.0,
    "ch102": 150.0,
    "ch103": 50.0,
    "ch104": 60.0,
    "ch105": 40.0,
    "ch106": 230.0,
    "ch107": 610.0,
    "ch108": 200.0,
    "ch109": 71730.0,
    "ch110": 150.0,
    "ch111": 35160.0,
    "ch112": 33390.0,
    "ch113": 150.0,
    "ch114": 90.0,
    "ch115": 370.0,
    "ch116": 440.0,
    "ch117": 21490.0,
    "ch118": 0.0,
    "ch201": 16860.0,
    "ch202": 1220.0,
    "ch203": 4720.0,
    "ch204": 14590.0,
    "ch205": 371760.0,
    "ch206": 2160.0,
    "ch207": 26220.0,
    "ch208": 4820.0,
    "ch209": 370.0
  },
  "coincidences": {}
}