{
  "timestamp": "2026-04-25T05:45:17.223841Z",
  "channels": {
    "ch101": 230.0,
    "ch102": 120.0,
    "ch103": 10.0,
    "ch104": 10.0,
    "ch105": 50.0,
    "ch106": 130.0,
    "ch107": 570.0,
    "ch108": 210.0,
    "ch109": 71680.0,
    "ch110": 80.0,
    "ch111": 32690.0,
    "ch112": 31640.0,
    "ch113": 100.0,
    "ch114": 40.0,
    "ch115": 150.0,
    "ch116": 340.0,
    "ch117": 20680.0,
    "ch118": 20.0,
    "ch201": 16490.0,
    "ch202": 1600.0,
    "ch203": 4590.0,
    "ch204": 14290.0,
    "ch205": 379810.0,
    "ch206": 2890.0,
    "ch207": 25990.0,
    "ch208": 5480.0,
    "ch209": 530.0
  },
  "coincidences": {}
}